libfast5mod.abi3.so
fast5mod-1.0.5.dist-info/RECORD
fast5mod-1.0.5.dist-info/entry_points.txt
fast5mod-1.0.5.dist-info/WHEEL
fast5mod-1.0.5.dist-info/METADATA
fast5mod-1.0.5.dist-info/top_level.txt
fast5mod/executor.py
fast5mod/programs.py
fast5mod/fast5mod.py
fast5mod/common.py
fast5mod/__init__.py
