Metadata-Version: 2.1
Name: fast5mod
Version: 1.0.5
Summary: Extraction of modified base data from Guppy Fast5 output
Home-page: https://github.com/nanoporetech/fast5mod
Author: ont-research
License: UNKNOWN
Platform: UNKNOWN
Requires-Python: >=3.5.*,<3.9
Requires-Dist: cffi
Requires-Dist: numpy (==1.18.5)
Requires-Dist: mappy
Requires-Dist: ont-fast5-api (==3.0.0)
Requires-Dist: pysam (==0.16.0.1)
